tinycircuits_sx1505/__init__.py
tinycircuits_sx1505/tinycircuits_sx1505.py
tinycircuits_sx1505-0.0.3.dist-info/LICENSE
tinycircuits_sx1505-0.0.3.dist-info/METADATA
tinycircuits_sx1505-0.0.3.dist-info/WHEEL
tinycircuits_sx1505-0.0.3.dist-info/top_level.txt
tinycircuits_sx1505-0.0.3.dist-info/RECORD
