Metadata-Version: 2.1
Name: tinycircuits-sx1505
Version: 0.0.3
Summary: SX1505 Joystick & Rotary Python library
Home-page: https://github.com/TinyCircuits/TinyCircuits-SX1505-Python
Author: TinyCircuits
Author-email: info@tinycircuits.com
License: UNKNOWN
Platform: UNKNOWN
Classifier: Programming Language :: Python :: 3
Classifier: License :: OSI Approved :: GNU General Public License v3 (GPLv3)
Classifier: Operating System :: OS Independent
Requires-Python: >=3.6
